pyruhvro-0.2.0.dist-info/METADATA
pyruhvro-0.2.0.dist-info/WHEEL
pyruhvro/__init__.py
pyruhvro/pyruhvro.cpython-38-aarch64-linux-gnu.so
pyruhvro-0.2.0.dist-info/RECORD
