Metadata-Version: 2.3
Name: pyruhvro
Version: 0.2.0
Classifier: Programming Language :: Rust
Classifier: Programming Language :: Python :: Implementation :: CPython
Classifier: Programming Language :: Python :: Implementation :: PyPy
Summary: Fast, multi-threaded deserialization of schema-less avro encoded messages
Keywords: avro,arrow,kafka
Author-email: Tyler Schauer <tylerschauer@gmail.com>
Requires-Python: >=3.8
Project-URL: Homepage, https://github.com/Tyler-Sch/pyruhvro
